vigilant_crypto_snatch/__init__.py
vigilant_crypto_snatch/cli.py
vigilant_crypto_snatch/commands/__init__.py
vigilant_crypto_snatch/commands/test_commands.py
vigilant_crypto_snatch/commands/testdrive.py
vigilant_crypto_snatch/commands/watch.py
vigilant_crypto_snatch/configuration/__init__.py
vigilant_crypto_snatch/configuration/interface.py
vigilant_crypto_snatch/configuration/migrations.py
vigilant_crypto_snatch/configuration/test_used_currencies.py
vigilant_crypto_snatch/configuration/test_yaml_configuration.py
vigilant_crypto_snatch/configuration/yaml_configuration.py
vigilant_crypto_snatch/core.py
vigilant_crypto_snatch/datastorage/__init__.py
vigilant_crypto_snatch/datastorage/factory.py
vigilant_crypto_snatch/datastorage/interface.py
vigilant_crypto_snatch/datastorage/list_store.py
vigilant_crypto_snatch/datastorage/sqlalchemy_store.py
vigilant_crypto_snatch/datastorage/test_implementations.py
vigilant_crypto_snatch/datastorage/test_sqlalchemy_store.py
vigilant_crypto_snatch/evaluation/__init__.py
vigilant_crypto_snatch/evaluation/close_chart.py
vigilant_crypto_snatch/evaluation/currency_pairs.py
vigilant_crypto_snatch/evaluation/drop_survey.py
vigilant_crypto_snatch/evaluation/feargreed_chart.py
vigilant_crypto_snatch/evaluation/market_simulation.py
vigilant_crypto_snatch/evaluation/price_data.py
vigilant_crypto_snatch/evaluation/test_close_chart.py
vigilant_crypto_snatch/evaluation/test_currency_pairs.py
vigilant_crypto_snatch/evaluation/test_drop_survey.py
vigilant_crypto_snatch/evaluation/test_market_simulation.py
vigilant_crypto_snatch/evaluation/test_price_data.py
vigilant_crypto_snatch/feargreed/__init__.py
vigilant_crypto_snatch/feargreed/alternateme.py
vigilant_crypto_snatch/feargreed/interface.py
vigilant_crypto_snatch/feargreed/test_alternateme.py
vigilant_crypto_snatch/historical/__init__.py
vigilant_crypto_snatch/historical/concrete.py
vigilant_crypto_snatch/historical/interface.py
vigilant_crypto_snatch/historical/mock.py
vigilant_crypto_snatch-5.9.3.dist-info/METADATA
vigilant_crypto_snatch-5.9.3.dist-info/WHEEL
vigilant_crypto_snatch-5.9.3.dist-info/entry_points.txt
vigilant_crypto_snatch-5.9.3.dist-info/RECORD
